Metadata-Version: 2.1
Name: jupyterhub-feishu-oauthenticator
Version: 0.0.1
Summary: FeiShu OAuthenticator for Jupyterhub
Home-page: https://github.com/tezignlab/jupyterhub_feishu_authenticator
Author: Tezign
Author-email: support@tezign.com
License: UNKNOWN
Platform: UNKNOWN
